gab_tidy_data/__init__.py
gab_tidy_data/__main__.py
gab_tidy_data/gab_data_mapping.py
gab_tidy_data/gab_schema.sql
gab_tidy_data/gab_to_sqlite.py
gab_tidy_data-0.1.0.dist-info/LICENSE
gab_tidy_data-0.1.0.dist-info/METADATA
gab_tidy_data-0.1.0.dist-info/WHEEL
gab_tidy_data-0.1.0.dist-info/entry_points.txt
gab_tidy_data-0.1.0.dist-info/top_level.txt
gab_tidy_data-0.1.0.dist-info/RECORD
