Metadata-Version: 2.1
Name: gab-tidy-data
Version: 0.1.0
Summary: Python script to take gab data (from Garc) and put it into a relational SQLite database 
Home-page: https://github.com/QUT-Digital-Observatory/gab_tidy_data
Author: QUT Digital Observatory
Author-email: digitalobservatory@qut.edu.au
License: MIT
Platform: UNKNOWN
Classifier: Development Status :: 3 - Alpha
Classifier: Programming Language :: Python :: 3
Classifier: License :: OSI Approved :: MIT License
Classifier: Intended Audience :: Science/Research
Classifier: Topic :: Sociology
Requires-Python: >=3.8
License-File: LICENSE
Requires-Dist: click (>=8.0.1)
Provides-Extra: develop
Requires-Dist: nox ; extra == 'develop'
Requires-Dist: flake8 ; extra == 'develop'
Requires-Dist: black ; extra == 'develop'
Provides-Extra: test
Requires-Dist: pytest ; extra == 'test'
Requires-Dist: nox ; extra == 'test'
